{
  "login": "waqar10",
  "id": 44400306,
  "node_id": "MDQ6VXNlcjQ0NDAwMzA2",
  "avatar_url": "https://avatars2.githubusercontent.com/u/44400306?v=4",
  "gravatar_id": "",
  "url": "https://api.github.com/users/waqar10",
  "html_url": "https://github.com/waqar10",
  "followers_url": "https://api.github.com/users/waqar10/followers",
  "following_url": "https://api.github.com/users/waqar10/following{/other_user}",
  "gists_url": "https://api.github.com/users/waqar10/gists{/gist_id}",
  "starred_url": "https://api.github.com/users/waqar10/starred{/owner}{/repo}",
  "subscriptions_url": "https://api.github.com/users/waqar10/subscriptions",
  "organizations_url": "https://api.github.com/users/waqar10/orgs",
  "repos_url": "https://api.github.com/users/waqar10/repos",
  "events_url": "https://api.github.com/users/waqar10/events{/privacy}",
  "received_events_url": "https://api.github.com/users/waqar10/received_events",
  "type": "User",
  "site_admin": false,
  "name": null,
  "company": null,
  "blog": "",
  "location": null,
  "email": null,
  "hireable": null,
  "bio": null,
  "public_repos": 19,
  "public_gists": 0,
  "followers": 1,
  "following": 0,
  "created_at": "2018-10-23T11:25:53Z",
  "updated_at": "2018-12-19T13:36:02Z"
}